{
  "generated_at": "2026-05-29T05:00:00.421380+00:00",
  "station": "Baierbrunn",
  "months": [
    {
      "period": "2026-05",
      "finalized": false,
      "total": 2400,
      "on_time": 564,
      "late": 1773,
      "cancelled": 63,
      "avg_delay_min": 3.0,
      "by_direction": {
        "muenchen": {
          "total": 1177,
          "on_time": 340,
          "late": 804,
          "cancelled": 33,
          "avg_delay_min": 2.2
        },
        "wolfratshausen": {
          "total": 1212,
          "on_time": 221,
          "late": 961,
          "cancelled": 30,
          "avg_delay_min": 3.8
        }
      }
    }
  ]
}