{
  "generated_at": "2026-05-25T20:00:00.389620+00:00",
  "station": "Baierbrunn",
  "months": [
    {
      "period": "2026-05",
      "finalized": false,
      "total": 2016,
      "on_time": 498,
      "late": 1470,
      "cancelled": 48,
      "avg_delay_min": 2.7,
      "by_direction": {
        "muenchen": {
          "total": 983,
          "on_time": 289,
          "late": 669,
          "cancelled": 25,
          "avg_delay_min": 2.1
        },
        "wolfratshausen": {
          "total": 1022,
          "on_time": 206,
          "late": 793,
          "cancelled": 23,
          "avg_delay_min": 3.3
        }
      }
    }
  ]
}