{
  "generated_at": "2026-06-13T17:00:00.404555+00:00",
  "station": "Baierbrunn",
  "months": [
    {
      "period": "2026-05",
      "finalized": true,
      "total": 2713,
      "on_time": 640,
      "late": 2010,
      "cancelled": 63,
      "avg_delay_min": 3.0,
      "by_direction": {
        "muenchen": {
          "total": 1334,
          "on_time": 384,
          "late": 917,
          "cancelled": 33,
          "avg_delay_min": 2.1
        },
        "wolfratshausen": {
          "total": 1368,
          "on_time": 253,
          "late": 1085,
          "cancelled": 30,
          "avg_delay_min": 3.9
        }
      }
    },
    {
      "period": "2026-06",
      "finalized": false,
      "total": 1432,
      "on_time": 312,
      "late": 1068,
      "cancelled": 52,
      "avg_delay_min": 2.7,
      "by_direction": {
        "muenchen": {
          "total": 705,
          "on_time": 165,
          "late": 512,
          "cancelled": 28,
          "avg_delay_min": 2.4
        },
        "wolfratshausen": {
          "total": 707,
          "on_time": 143,
          "late": 540,
          "cancelled": 24,
          "avg_delay_min": 3.0
        }
      }
    }
  ]
}