{
  "generated_at": "2026-06-22T06:00:00.435177+00:00",
  "station": "Baierbrunn",
  "months": [
    {
      "period": "2026-05",
      "finalized": true,
      "total": 2713,
      "on_time": 640,
      "late": 2010,
      "cancelled": 63,
      "avg_delay_min": 3.0,
      "by_direction": {
        "muenchen": {
          "total": 1334,
          "on_time": 384,
          "late": 917,
          "cancelled": 33,
          "avg_delay_min": 2.1
        },
        "wolfratshausen": {
          "total": 1368,
          "on_time": 253,
          "late": 1085,
          "cancelled": 30,
          "avg_delay_min": 3.9
        }
      }
    },
    {
      "period": "2026-06",
      "finalized": false,
      "total": 2236,
      "on_time": 564,
      "late": 1598,
      "cancelled": 74,
      "avg_delay_min": 2.6,
      "by_direction": {
        "muenchen": {
          "total": 1116,
          "on_time": 316,
          "late": 760,
          "cancelled": 40,
          "avg_delay_min": 2.2
        },
        "wolfratshausen": {
          "total": 1100,
          "on_time": 244,
          "late": 822,
          "cancelled": 34,
          "avg_delay_min": 3.1
        }
      }
    }
  ]
}